{
    "CH89RealCentral": {
        "V_0": 55.7463,
        "V_t": 9.56057,
        "V_e": -0.302119,
        "r_o": 1.20899,
        "r_o_0": -0.307169,
        "a_0": 0.732093
    },
    "CH89Coulomb": {
        "r_c": 1.44161,
        "r_c_0": 0.210779
    },
    "CH89SpinOrbit": {
        "V_so": 5.82354,
        "r_so": 1.55961,
        "r_so_0": -2.23382,
        "a_so": 0.570128
    },
    "CH89ImagCentral": {
        "W_v0": 10.9105,
        "W_ve0": 25.0826,
        "W_vew": 27.913,
        "W_s0": 5.82692,
        "W_st": 22.755,
        "W_se0": 31.5837,
        "W_sew": 14.4548,
        "r_w": 1.28056,
        "r_w0": 0.0432112,
        "a_w": 0.707159
    }
}