{
    "CH89RealCentral": {
        "V_0": 54.0679,
        "V_t": 20.843,
        "V_e": -0.304876,
        "r_o": 1.16167,
        "r_o_0": -0.0131079,
        "a_0": 0.698896
    },
    "CH89Coulomb": {
        "r_c": 1.35584,
        "r_c_0": 0.147826
    },
    "CH89SpinOrbit": {
        "V_so": 3.7497,
        "r_so": 1.29526,
        "r_so_0": -1.03692,
        "a_so": 0.616154
    },
    "CH89ImagCentral": {
        "W_v0": 12.9938,
        "W_ve0": 44.8092,
        "W_vew": 25.9055,
        "W_s0": 10.6494,
        "W_st": 36.4356,
        "W_se0": 15.3895,
        "W_sew": 34.9037,
        "r_w": 1.29618,
        "r_w0": -0.379514,
        "a_w": 0.692276
    }
}