{
    "CH89RealCentral": {
        "V_0": 57.4261,
        "V_t": 21.0139,
        "V_e": -0.349584,
        "r_o": 1.17908,
        "r_o_0": -0.197467,
        "a_0": 0.76652
    },
    "CH89Coulomb": {
        "r_c": 1.26703,
        "r_c_0": -0.0878862
    },
    "CH89SpinOrbit": {
        "V_so": 5.93021,
        "r_so": 1.30539,
        "r_so_0": -0.850987,
        "a_so": 0.59423
    },
    "CH89ImagCentral": {
        "W_v0": 6.76316,
        "W_ve0": 56.3507,
        "W_vew": 11.2362,
        "W_s0": 12.729,
        "W_st": 24.7608,
        "W_se0": 34.0893,
        "W_sew": 52.4827,
        "r_w": 1.19619,
        "r_w0": -0.171261,
        "a_w": 0.756484
    }
}